<annotation>
	<folder>train</folder>
	<filename>702.jpg</filename>
	<path>/home/redteam/i-n eed-2021/object_detection_demo-master/data/images/train/702.jpg</path>
	<source>
		<database>Unknown</database>
	</source>
	<size>
		<width>800</width>
		<height>600</height>
		<depth>3</depth>
	</size>
	<segmented>0</segmented>
	<object>
		<name>crowbar</name>
		<pose>Unspecified</pose>
		<truncated>0</truncated>
		<difficult>0</difficult>
		<bndbox>
			<xmin>363</xmin>
			<ymin>371</ymin>
			<xmax>494</xmax>
			<ymax>480</ymax>
		</bndbox>
	</object>
	<object>
		<name>weapon</name>
		<pose>Unspecified</pose>
		<truncated>0</truncated>
		<difficult>0</difficult>
		<bndbox>
			<xmin>354</xmin>
			<ymin>363</ymin>
			<xmax>506</xmax>
			<ymax>489</ymax>
		</bndbox>
	</object>
	<object>
		<name>intruder</name>
		<pose>Unspecified</pose>
		<truncated>0</truncated>
		<difficult>0</difficult>
		<bndbox>
			<xmin>386</xmin>
			<ymin>2</ymin>
			<xmax>481</xmax>
			<ymax>527</ymax>
		</bndbox>
	</object>
	<object>
		<name>door</name>
		<pose>Unspecified</pose>
		<truncated>1</truncated>
		<difficult>0</difficult>
		<bndbox>
			<xmin>362</xmin>
			<ymin>5</ymin>
			<xmax>800</xmax>
			<ymax>555</ymax>
		</bndbox>
	</object>
	<object>
		<name>breach</name>
		<pose>Unspecified</pose>
		<truncated>0</truncated>
		<difficult>0</difficult>
		<bndbox>
			<xmin>330</xmin>
			<ymin>8</ymin>
			<xmax>536</xmax>
			<ymax>538</ymax>
		</bndbox>
	</object>
	<object>
		<name>threat</name>
		<pose>Unspecified</pose>
		<truncated>1</truncated>
		<difficult>0</difficult>
		<bndbox>
			<xmin>306</xmin>
			<ymin>1</ymin>
			<xmax>577</xmax>
			<ymax>557</ymax>
		</bndbox>
	</object>
</annotation>
