<annotation>
	<folder>test</folder>
	<filename>guns37.jpg</filename>
	<path>/root/object_detection_demo-master/data/images/test/guns37.jpg</path>
	<source>
		<database>Unknown</database>
	</source>
	<size>
		<width>283</width>
		<height>178</height>
		<depth>3</depth>
	</size>
	<segmented>0</segmented>
	<object>
		<name>shotgun</name>
		<pose>Unspecified</pose>
		<truncated>0</truncated>
		<difficult>0</difficult>
		<bndbox>
			<xmin>14</xmin>
			<ymin>5</ymin>
			<xmax>246</xmax>
			<ymax>155</ymax>
		</bndbox>
	</object>
	<object>
		<name>person</name>
		<pose>Unspecified</pose>
		<truncated>1</truncated>
		<difficult>0</difficult>
		<bndbox>
			<xmin>100</xmin>
			<ymin>1</ymin>
			<xmax>213</xmax>
			<ymax>178</ymax>
		</bndbox>
	</object>
	<object>
		<name>THREAT !!</name>
		<pose>Unspecified</pose>
		<truncated>0</truncated>
		<difficult>0</difficult>
		<bndbox>
			<xmin>10</xmin>
			<ymin>3</ymin>
			<xmax>261</xmax>
			<ymax>174</ymax>
		</bndbox>
	</object>
</annotation>
